py_bdd_context/__init__.py
py_bdd_context/bdd_context.py
py_bdd_context/test_case.py
py_bdd_context/test_file_helper.py
py_bdd_context-0.0.4.dist-info/entry_points.txt
py_bdd_context-0.0.4.dist-info/WHEEL
py_bdd_context-0.0.4.dist-info/METADATA
py_bdd_context-0.0.4.dist-info/RECORD
